dac_ycl/__init__.py
dac_ycl/glc/__init__.py
dac_ycl/glc/glc_bd4r_trend.py
dac_ycl/glc/glc_bw1r_trend.py
dac_ycl/glc/glc_control.py
dac_ycl/glc/glc_d3lr_trend.py
dac_ycl/glc/glc_sum2cp_trend.py
dac_ycl/glc/glc_ycl_trend.py
dac_ycl/glc/utils/__init__.py
dac_ycl/glc/utils/control_delta.py
dac_ycl/glc/utils/dac_facade.py
dac_ycl/glc/utils/fake_cache.py
dac_ycl/glc/utils/ycl_abandon_abnormal.py
dac_ycl/jwd_ce/ce_control.py
dac_ycl/jwd_ce/jwd3.py
dac_ycl/jwd_ce/jwd_d3lr_trend.py
dac_ycl/jwd_ce/jwd_ycl_trend.py
dac_ycl/jwd_ce/utils/__init__.py
dac_ycl/jwd_ce/utils/config.py
dac_ycl/jwd_ce/utils/control_delta.py
dac_ycl/jwd_ce/utils/dac_facade.py
dac_ycl/jwd_ce/utils/mysql_util.py
dac_ycl/jwd_ce/utils/ycl_abandon_abnormal.py
dac_ycl/lqd/__init__.py
dac_ycl/lqd/lqd_1010.py
dac_ycl/lqd/utils/__init__.py
dac_ycl/lqd/utils/control_delta.py
dac_ycl/lqd/utils/dac_facade.py
dac_ycl/lqd/utils/fake_cache.py
dac_ycl/lqd/utils/ycl_abandon_abnormal.py
dac_ycl-0.1.6.dist-info/METADATA
dac_ycl-0.1.6.dist-info/WHEEL
dac_ycl-0.1.6.dist-info/RECORD
