Metadata-Version: 2.1
Name: dac-ycl
Version: 0.1.6
Summary: hy ycl testing dependencies
Author: Li xin
Author-email: xin.li@zhan-wan.com
Requires-Python: >=3.10.1,<4.0.0
Classifier: Programming Language :: Python :: 3
Classifier: Programming Language :: Python :: 3.11
Classifier: Programming Language :: Python :: 3.12
Requires-Dist: numpy
Requires-Dist: openpyxl
Requires-Dist: pandas
Requires-Dist: plotly
Requires-Dist: pymysql
Requires-Dist: redis
Requires-Dist: scipy
